{
  "BTCUSDT": {
    "ts": 1765735525.6384156,
    "signal": {
      "active": true,
      "direction": "LONG",
      "confidence": 0.129,
      "hurst_value": 0.4394,
      "regime": "mean_reverting",
      "interpretation": "Market mean-reverting (0.44), fade to LONG",
      "trend_direction": "SHORT",
      "trend_strength": 0.531,
      "timestamp": "2025-12-14T18:05:25.730352"
    }
  },
  "ETHUSDT": {
    "ts": 1765735400.646344,
    "signal": {
      "active": true,
      "direction": "LONG",
      "confidence": 0.143,
      "hurst_value": 0.4301,
      "regime": "mean_reverting",
      "interpretation": "Market mean-reverting (0.43), fade to LONG",
      "trend_direction": "SHORT",
      "trend_strength": 0.512,
      "timestamp": "2025-12-14T18:03:20.746514"
    }
  },
  "SOLUSDT": {
    "ts": 1765735804.8348653,
    "signal": {
      "active": false,
      "direction": "SHORT",
      "confidence": 0.3,
      "hurst_value": 0.5272,
      "regime": "random",
      "interpretation": "Market random walk (0.53), low confidence",
      "trend_direction": "SHORT",
      "trend_strength": 0.542,
      "timestamp": "2025-12-14T18:10:05.097505"
    }
  },
  "AVAXUSDT": {
    "ts": 1765735539.5190308,
    "signal": {
      "active": false,
      "direction": "SHORT",
      "confidence": 0.3,
      "hurst_value": 0.5451,
      "regime": "random",
      "interpretation": "Market random walk (0.55), low confidence",
      "trend_direction": "SHORT",
      "trend_strength": 0.525,
      "timestamp": "2025-12-14T18:05:39.632066"
    }
  },
  "DOTUSDT": {
    "ts": 1765735011.3140526,
    "signal": {
      "active": true,
      "direction": "LONG",
      "confidence": 0.304,
      "hurst_value": 0.3702,
      "regime": "mean_reverting",
      "interpretation": "Market mean-reverting (0.37), fade to LONG",
      "trend_direction": "SHORT",
      "trend_strength": 0.586,
      "timestamp": "2025-12-14T17:56:51.414547"
    }
  },
  "XRPUSDT": {
    "ts": 1765735412.7780082,
    "signal": {
      "active": false,
      "direction": "SHORT",
      "confidence": 0.3,
      "hurst_value": 0.4919,
      "regime": "random",
      "interpretation": "Market random walk (0.49), low confidence",
      "trend_direction": "SHORT",
      "trend_strength": 0.528,
      "timestamp": "2025-12-14T18:03:32.875025"
    }
  },
  "DOGEUSDT": {
    "ts": 1765735416.5526433,
    "signal": {
      "active": false,
      "direction": "SHORT",
      "confidence": 0.3,
      "hurst_value": 0.5035,
      "regime": "random",
      "interpretation": "Market random walk (0.50), low confidence",
      "trend_direction": "SHORT",
      "trend_strength": 0.601,
      "timestamp": "2025-12-14T18:03:36.672612"
    }
  },
  "ADAUSDT": {
    "ts": 1765735549.289745,
    "signal": {
      "active": false,
      "direction": "SHORT",
      "confidence": 0.3,
      "hurst_value": 0.5234,
      "regime": "random",
      "interpretation": "Market random walk (0.52), low confidence",
      "trend_direction": "SHORT",
      "trend_strength": 0.577,
      "timestamp": "2025-12-14T18:05:49.402234"
    }
  },
  "BNBUSDT": {
    "ts": 1765735419.5958316,
    "signal": {
      "active": true,
      "direction": "LONG",
      "confidence": 0.195,
      "hurst_value": 0.4106,
      "regime": "mean_reverting",
      "interpretation": "Market mean-reverting (0.41), fade to LONG",
      "trend_direction": "SHORT",
      "trend_strength": 0.545,
      "timestamp": "2025-12-14T18:03:39.731907"
    }
  }
}